spongebobify/__init__.py
spongebobify/__main__.py
spongebobify/main.py
spongebobify-1.0.0.dist-info/LICENSE.md
spongebobify-1.0.0.dist-info/METADATA
spongebobify-1.0.0.dist-info/WHEEL
spongebobify-1.0.0.dist-info/entry_points.txt
spongebobify-1.0.0.dist-info/RECORD
