Metadata-Version: 2.3
Name: spongebobify
Version: 1.0.0
Summary: Are ya ready kids? aYE AyE! You can now make your text...sARcaStiC!
License: MIT
Author: Michael Gray
Author-email: mike@graywind.org
Requires-Python: >=3.10,<4.0
Classifier: License :: OSI Approved :: MIT License
Classifier: Programming Language :: Python :: 3
Classifier: Programming Language :: Python :: 3.10
Classifier: Programming Language :: Python :: 3.11
Classifier: Programming Language :: Python :: 3.12
Classifier: Programming Language :: Python :: 3.13
Project-URL: Repository, https://github.com/mikejgray/spongebobify
